LICENSE
MANIFEST.in
README.rst
setup.py
django_ripple.egg-info/PKG-INFO
django_ripple.egg-info/SOURCES.txt
django_ripple.egg-info/dependency_links.txt
django_ripple.egg-info/top_level.txt
ripple/GaeSettings.py
ripple/LocalSettings.py
ripple/MailFilter.py
ripple/__init__.py
ripple/admin.py
ripple/apps.py
ripple/assets.py
ripple/auth.py
ripple/context.py
ripple/errorcodes.py
ripple/middleware.py
ripple/models.py
ripple/serializers.py
ripple/urls.py
ripple/validators.py
ripple/views.py
ripple/appengine_emailbackend/__init__.py
ripple/appengine_emailbackend/async.py
ripple/appengine_emailbackend/default.py
ripple/management/__init__.py
ripple/management/commands/__init__.py
ripple/management/commands/start_ripple_project.py
ripple/migrations/0001_initial.py
ripple/migrations/0002_user_phone_number.py
ripple/migrations/0003_featureoption_featureurl.py
ripple/migrations/0004_auto_20200402_1411.py
ripple/migrations/0005_user_is_guest.py
ripple/migrations/0006_auto_20201106_1649.py
ripple/migrations/__init__.py
ripple/templates/ripplebase.html
ripple/templates/robots.txt
ripple/tests/__init__.py
ripple/tests/base.py
ripple/tests/factories.py
ripple/tests/test_views.py
ripple/tests/utils.py