Metadata-Version: 1.1
Name: django-ripple
Version: 0.4.4
Summary: Django-React-Bootstrap Framework Django Component
Home-page: https://www.rippleenergy.com/
Author: Miklos Parrag
Author-email: miklos.parrage@gmail.com
License: ISC License
Platform: UNKNOWN
Classifier: Environment :: Web Environment
Classifier: Framework :: Django
Classifier: Framework :: Django :: 2.1
Classifier: Intended Audience :: Developers
Classifier: License :: OSI Approved :: BSD License
Classifier: Operating System :: OS Independent
Classifier: Programming Language :: Python
Classifier: Programming Language :: Python :: 3.5
Classifier: Programming Language :: Python :: 3.6
Classifier: Topic :: Internet :: WWW/HTTP
Classifier: Topic :: Internet :: WWW/HTTP :: Dynamic Content
